__init__.py
agentbeats/__init__.py
agentbeats/backend.py
agentbeats/cli.py
agentbeats/controller.py
agentbeats/gcp.py
agentbeats/model.py
agentbeats/runner.py
agentbeats/frontend/agent_crud.html
agentbeats/frontend/ctrl_info.html
earthshaker-0.1.12.dist-info/METADATA
earthshaker-0.1.12.dist-info/WHEEL
earthshaker-0.1.12.dist-info/entry_points.txt
earthshaker-0.1.12.dist-info/top_level.txt
earthshaker-0.1.12.dist-info/RECORD
