Metadata-Version: 2.4
Name: earthshaker
Version: 0.1.12
Summary: New Impl for Project AgentBeats
Requires-Python: >=3.13
Requires-Dist: a2a-sdk[http-server]>=0.3.10
Requires-Dist: docker>=7.1.0
Requires-Dist: fastapi[standard]>=0.120.3
Requires-Dist: google-cloud-run>=0.12.0
Requires-Dist: pydantic-settings>=2.11.0
Requires-Dist: python-dotenv>=1.2.1
Requires-Dist: sqlmodel>=0.0.27
Requires-Dist: typer>=0.20.0
